<scene>
	<lights>
			<light type="DIRECTIONAL"  X="0" Y="0" Z="71" />
	</lights>
	<group>
		<scale X="0.3" Y="0.3" Z="0.3"/>	
		<models>
			<model file="sun.3d"  texture= "sun.jpg"/>
		</models>

		<group>
			<rotate time="29.3233"  axisY="1" />
			<translate  Z="109" />
			<rotate time="19.387"  axisY="1" />
			<models>
				<model file="mercury.3d" texture= "mercury.jpg" />
			</models>
		</group>

		<group>
			<rotate time="74.9000"  axisY="1" />
			<translate  Z="142" />
			<rotate time="74.9"  axisY="1" />
			<models>
				<model file="venus.3d" texture= "venus.jpg" />
			</models>
		</group>

		<group>
			<rotate time="121.6667"  axisY="1" />
			<translate  Z="170" />
			<rotate time="19.387"  axisY="1" />
			<models>
				<model file="earth.3d" texture= "earth.jpg" />
			</models>
		</group>

		<group>
			<rotate time="121.6667"  axisY="1" />
			<translate  Z="170" />
			<rotate time="27,77"  axisY="1" />
			<translate  Z="8" />
			<rotate time="19.387"  axisY="1" />

			<models>
				<model file="lua.3d" texture="moon.jpg"/>
			</models>
		</group>

		<group>
			<rotate time="128.9933"  axisY="1" />
			<translate  Z="222" />
			<rotate time="0.3333"  axisY="1" />

			<models>
				<model file="mars.3d" texture="mars.jpg"/>
			</models>
		</group>
		<group>
			<color R="0.75" G="0.75" B="0.75" />
			<rotate time="128.9933"  axisY="1" />
			<translate  Z="222" />
			<rotate time="27,77"  axisY="1" />
			<translate  Z="-4" />
			<scale X="0.5" Y= "0.5" Z="0.5" />
			<models>
				<model file="marsmoons.3d" />
			</models>
		</group>
		<group>
			<rotate time="128.9933"  axisY="1" />
			<translate  Z="222" />
			<rotate time="27,77"  axisY="1" />
			<translate  X="3" Z="5" />
			<scale X="2" Y= "2" Z="2" />
			<models>
				<model file="marsmoons.3d" />
			</models>
		</group>
		<group>
			<rotate time="433"  axisY="1" />
			<translate  Z="329" />
			<models>
				<model file="jupiter.3d" texture="jupiter.jpg" />
			</models>
		</group>
		<group>
			<color r="0.8" G="0.8" B="0.9" />
			<rotate time="433"  axisY="1" />
			<translate  Z="329" />
			<translate  Z="4" />
			<scale X="2" Y= "2" Z="2" />
			<models>
				<model file="jupitermoons.3d" />
			</models>
		</group>
		<group>
			<color R="0.85" G="0.75" B="0.95" />
			<rotate time="433"  axisY="1" />
			<translate  Z="329" />
			<translate  X="12" Y="15" Z="5" />
			<scale X="5" Y= "5" Z="5" />
			<models>
				<model file="jupitermoons.3d" />
			</models>
		</group>

		<group>
			<color R="0.93" G="0.91" B="0.67" />
			<rotate time="538.375"  axisY="1" />
			<translate  Z="549" />
			<rotate time="2.13888"  axisY="1" />

			<models>
				<model file="saturn.3d" texture="saturn.jpg"/>
			</models>
		</group>
		<group>
			<color R="0.98" G="0.92" B="0.84" />
			
			<rotate time="538.375"  axisY="1" />
			
			<rotate angle="-60" X= "0" Y="1" Z="0" />
			<translate  Z="549" />
		
			<models>
				<model file="ring.3d" texture="saturnring.png"/>
			</models>
		</group>
				
		<group>
			
			<rotate time="613.28"  axisY="1" />
			<translate  Z="770" />
			<rotate time="0.16986"  axisY="1" />

			<models>
				<model file="uranus.3d" texture="uranus.jpg" />
			</models>
		</group>

		<group>
			<rotate time="669.1667"  axisY="1" />
			<translate  Z="910" />
			<rotate time="0.6667"  axisY="1" />

			<models>
				<model file="neptune.3d" texture="neptune.jpg" />
			</models>
		</group>		

	</group>
</scene>